example/__init__.py
example/main.py
example/original.xml
example/schema.py
example/webservice.py
fastapi_soap-0.2.0.dist-info/METADATA
fastapi_soap-0.2.0.dist-info/WHEEL
fastapi_soap-0.2.0.dist-info/entry_points.txt
fastapi_soap-0.2.0.dist-info/licenses/LICENCE
fastapi_soap/__init__.py
fastapi_soap/exceptions.py
fastapi_soap/models.py
fastapi_soap/request.py
fastapi_soap/response.py
fastapi_soap/routes.py
fastapi_soap/wsdl.py
fastapi_soap-0.2.0.dist-info/RECORD
