Metadata-Version: 2.1
Name: fastapi-soap
Version: 0.2.0
Author-Email: Cleiton Mittmann <mittmannv8@gmail.com>
Classifier: Development Status :: 4 - Beta
Classifier: Environment :: Web Environment
Classifier: Framework :: FastAPI
Classifier: Framework :: Pydantic
Classifier: License :: OSI Approved :: MIT License
Classifier: Topic :: Internet
Classifier: Topic :: Internet :: WWW/HTTP
Classifier: Topic :: Software Development :: Libraries
Classifier: Topic :: Software Development :: Libraries :: Python Modules
Classifier: Intended Audience :: Developers
Classifier: Operating System :: OS Independent
Classifier: Programming Language :: Python :: 3.10
Requires-Python: >=3.10
Requires-Dist: fastapi>=0.115.13
Requires-Dist: lxml>=5.4.0
Requires-Dist: pydantic>=2.11.7
Requires-Dist: pydantic-xml>=2.17.2
